ism.py
inspur_sm_sdk/__init__.py
inspur_sm_sdk/command/IpmiFunc.py
inspur_sm_sdk/command/RedfishFunc.py
inspur_sm_sdk/command/RestFunc.py
inspur_sm_sdk/command/__init__.py
inspur_sm_sdk/command/backup.py
inspur_sm_sdk/command/restore.py
inspur_sm_sdk/command/M5Log/__init__.py
inspur_sm_sdk/command/M5Log/biosPostEventStr.py
inspur_sm_sdk/command/M5Log/commonInfoStr.py
inspur_sm_sdk/command/M5Log/eventLogString.py
inspur_sm_sdk/command/M5Log/sensorEventStr.py
inspur_sm_sdk/command/M5Log/sensorSpecificEventStr.py
inspur_sm_sdk/command/M5Log/showSensorDesc.py
inspur_sm_sdk/command/bios/A7.xml
inspur_sm_sdk/command/bios/M4.xml
inspur_sm_sdk/command/bios/M5.xml
inspur_sm_sdk/command/bios/M6-N.xml
inspur_sm_sdk/command/bios/M6.xml
inspur_sm_sdk/command/bios/M7.xml
inspur_sm_sdk/command/bios/M7_5.10.00.xml
inspur_sm_sdk/command/bios/NF3180A6.xml
inspur_sm_sdk/command/bios/NF3280A6.xml
inspur_sm_sdk/command/bios/NF5180M5.xml
inspur_sm_sdk/command/bios/NF5280M5.xml
inspur_sm_sdk/command/bios/NF5468A5.xml
inspur_sm_sdk/command/bios/NF5488A5.xml
inspur_sm_sdk/command/bios/SA5112M5.xml
inspur_sm_sdk/command/bios/SA5212M5.xml
inspur_sm_sdk/interface/Base.py
inspur_sm_sdk/interface/CommonA5.py
inspur_sm_sdk/interface/CommonA6.py
inspur_sm_sdk/interface/CommonA7.py
inspur_sm_sdk/interface/CommonA7_11308.py
inspur_sm_sdk/interface/CommonM5.py
inspur_sm_sdk/interface/CommonM6.py
inspur_sm_sdk/interface/CommonM6_41401.py
inspur_sm_sdk/interface/CommonM6_4140a.py
inspur_sm_sdk/interface/CommonM7.py
inspur_sm_sdk/interface/CommonM7_13505.py
inspur_sm_sdk/interface/I24M6.py
inspur_sm_sdk/interface/IBase.py
inspur_sm_sdk/interface/NF5180M5.py
inspur_sm_sdk/interface/NF5180M5Impl.py
inspur_sm_sdk/interface/NF5280M5.py
inspur_sm_sdk/interface/NF5280M5Impl.py
inspur_sm_sdk/interface/NF5280M5_435.py
inspur_sm_sdk/interface/NF5280M5_436.py
inspur_sm_sdk/interface/NS5160M6.py
inspur_sm_sdk/interface/ResEntity.py
inspur_sm_sdk/interface/SA5212M5Impl.py
inspur_sm_sdk/interface/__init__.py
inspursmsdk-2.3.2.dist-info/LICENSE
inspursmsdk-2.3.2.dist-info/METADATA
inspursmsdk-2.3.2.dist-info/WHEEL
inspursmsdk-2.3.2.dist-info/top_level.txt
inspursmsdk-2.3.2.dist-info/RECORD
