Metadata-Version: 2.1
Name: inspursmsdk
Version: 2.3.2
Summary: inspur server manager api
Home-page: https://github.com/ISIB-Group/inspursmsdk
Author: Wangbaoshan
Author-email: wangbaoshan@inspur.com
License: Expat License
Platform: UNKNOWN
Classifier: Programming Language :: Python
Classifier: Programming Language :: Python :: 3
Classifier: Programming Language :: Python :: 3.4
Classifier: Programming Language :: Python :: 3.5
Classifier: Programming Language :: Python :: 3.6
Classifier: Programming Language :: Python :: 3.7
Classifier: Programming Language :: Python :: 3.8
Requires-Dist: pycryptodome (>=3.5.0)
Requires-Dist: PyYAML
Requires-Dist: requests (>=2.9.1)
Requires-Dist: Jpype1
Requires-Dist: requests-toolbelt
